Metadata-Version: 1.0
Name: copypathtoclipboard
Version: 3
Summary: Copy path to clipboard :)
Home-page: http://none.com
Author: Walter Mastrangelo
Author-email: walterjmas@gmail.com
License: MIT
Platform: UNKNOWN
